[{"name":"コトヤマ","_id":{"$oid":"5f9855bcb629d1a38d4cbd8e"}},{"name":"ZUN","_id":{"$oid":"5f9855bcb629d1a38d4cbd8f"}},{"name":"あずまあや","_id":{"$oid":"5f9855bcb629d1a38d4cbd90"}},{"name":"藤本タツキ","_id":{"$oid":"5f9855bcb629d1a38d4cbd91"}},{"name":"眉月じゅん","_id":{"$oid":"5f9855bcb629d1a38d4cbd92"}},{"name":"近藤笑真","_id":{"$oid":"5f9855bcb629d1a38d4cbd93"}},{"name":"窓口基","_id":{"$oid":"5f9855bcb629d1a38d4cbd94"}},{"name":"ブラッドレー・ボンド＋フィリップ・N・モーゼズ","_id":{"$oid":"5f9855bcb629d1a38d4cbd95"}},{"name":"余湖裕輝","_id":{"$oid":"5f9855bcb629d1a38d4cbd96"}},{"name":"田畑由秋","_id":{"$oid":"5f9855bcb629d1a38d4cbd97"}},{"name":"伊瀬 勝良","_id":{"$oid":"5f9855bcb629d1a38d4cbd98"}},{"name":"横田 卓馬","_id":{"$oid":"5f9855bcb629d1a38d4cbd99"}},{"name":"銀木犀","_id":{"$oid":"5f9855bcb629d1a38d4cbd9a"}},{"name":"水炊き","_id":{"$oid":"5f985f080bebe591425f7ac4"}},{"name":"鎌池 和馬","_id":{"$oid":"5f9855bcb629d1a38d4cbd9b"}},{"name":"冬川 基","_id":{"$oid":"5f9855bcb629d1a38d4cbd9c"}},{"name":"西尾 維新","_id":{"$oid":"5f9855bcb629d1a38d4cbd9d"}},{"name":"大暮 維人","_id":{"$oid":"5f9855bcb629d1a38d4cbd9e"}},{"name":"春河もえ","_id":{"$oid":"5f9855bcb629d1a38d4cbd9f"}},{"name":"あずまきよひこ","_id":{"$oid":"5f985f080bebe591425f7ac6"}},{"name":"大童澄瞳","_id":{"$oid":"5f985f080bebe591425f7ac5"}},{"name":"カズホ","_id":{"$oid":"5f985f080bebe591425f7ac6"}},{"name":"小野中彰大","_id":{"$oid":"5f985f080bebe591425f7ac8"}},{"name":"あらゐけいいち","_id":{"$oid":"5f985f080bebe591425f7ac9"}},{"name":"はいむら きよたか","_id":{"$oid":"5f985f080bebe591425f7aca"}}]